Metadata-Version: 2.1
Name: testflows.snapshots
Version: 1.0.241118.1153542
Summary: TestFlows - Snapshots
Home-page: https://github.com/testflows/testflows-snapshots
Author: Vitaliy Zakaznikov
Author-email: vzakaznikov@testflows.com
License: Apache-2.0
Platform: UNKNOWN
Classifier: Development Status :: 2 - Pre-Alpha
Classifier: Programming Language :: Python :: 3
Classifier: License :: OSI Approved :: Apache Software License
Classifier: Operating System :: POSIX :: Linux
Requires-Python: >=3.6
Provides-Extra: dev
License-File: LICENSE
